pyleotups/__init__.py
pyleotups/core/Dataset.py
pyleotups/core/__init__.py
pyleotups/tests/__init__.py
pyleotups/tests/test_Dataset.py
pyleotups/tests/test_NonStandardParser.py
pyleotups/tests/helpers/__init__.py
pyleotups/tests/helpers/mock_study_response.py
pyleotups/utils/NOAADataset.py
pyleotups/utils/PaleoData.py
pyleotups/utils/Publication.py
pyleotups/utils/Site.py
pyleotups/utils/__init__.py
pyleotups/utils/helpers.py
pyleotups/utils/Parser/NonStandardParser.py
pyleotups/utils/Parser/StandardParser.py
pyleotups/utils/Parser/__init__.py
pyleotups-0.0.1.dist-info/METADATA
pyleotups-0.0.1.dist-info/WHEEL
pyleotups-0.0.1.dist-info/top_level.txt
pyleotups-0.0.1.dist-info/RECORD
