Metadata-Version: 2.4
Name: pyleotups
Version: 0.0.1
Summary: Automated Paleoclimate Data Extraction and Processing
Author-email: Dhiren Oswal <linkedearth@gmail.com>, Deborah Khider <linkedearth@gmail.com>, Jay Pujara <linkedearth@gmail.com>
License: Apache License 2.0
Project-URL: Homepage, https://github.com/LinkedEarth/pyleotups/pyleotups
Keywords: pyleotups,Table Understanding,Data Analysis
Requires-Python: >=3.8
Requires-Dist: pandas==2.1.4
Requires-Dist: requests
Requires-Dist: numpy
Requires-Dist: pybtex
Requires-Dist: setuptools
Requires-Dist: tqdm
Requires-Dist: nbstripout
